dist/ka_uta-2023.2.1.tar.gz
ka_uta/__init__.py
ka_uta/__version__.py
ka_uta/d3v.py
ka_uta/ka_asyhttp.py
ka_uta/ka_csv.py
ka_uta/ka_email.py
ka_uta/ka_hf.py
ka_uta/ka_http.py
ka_uta/ka_jinja2.py
ka_uta/ka_json.py
ka_uta/ka_mgo.py
ka_uta/ka_nlp.py
ka_uta/ka_numpy.py
ka_uta/ka_os.py
ka_uta/ka_toml.py
ka_uta/ka_xlsx.py
ka_uta/ka_xml.py
ka_uta/ka_yaml.py
ka_uta/obj.py
ka_uta/py.typed
ka_uta/str.py
ka_uta/data/__init__.py
ka_uta/data/log.yml
ka_uta/data/pgu.yml
ka_uta-2023.2.1.dist-info/LICENSE.txt
ka_uta-2023.2.1.dist-info/METADATA
ka_uta-2023.2.1.dist-info/WHEEL
ka_uta-2023.2.1.dist-info/top_level.txt
ka_uta-2023.2.1.dist-info/RECORD
