Metadata-Version: 2.1
Name: ka-uta
Version: 2023.2.1
Summary: Application Utilities
Author-email: Bernd Stroehle <bernd.stroehle@bs29.com>
Maintainer-email: Bernd Stroehle <bernd.stroehle@bs29.com>
Project-URL: Source Code, https://github.com/bs29/ka_uta/tree/master
Project-URL: Homepage, https://kosakya.de/
Project-URL: Documentation, https://ka-uta.readthedocs.io/en/latest
Project-URL: Apache-2.0 License, https://apache.org/licenses/LICENSE-2.0
Classifier: Development Status :: 5 - Production/Stable
Classifier: Intended Audience :: Developers
Classifier: License :: OSI Approved :: Apache Software License
Classifier: Operating System :: OS Independent
Classifier: Programming Language :: Python :: 3.10
Classifier: Natural Language :: English
Classifier: Topic :: Software Development :: Libraries :: Python Modules
Requires-Python: >=3.10
License-File: LICENSE.txt
Requires-Dist: aiohttp (>=3.8.3)
Requires-Dist: distro (>=1.8.0)
Requires-Dist: email-validator (>=1.3.0)
Requires-Dist: humanfriendly (>=10.0)
Requires-Dist: Jinja2 (>=3.1.2)
Requires-Dist: ka-com (>=2023.2.1)
Requires-Dist: ka-utg (>=2023.2.2)
Requires-Dist: lxml (>=4.9.2)
Requires-Dist: numpy (>=1.24.1)
Requires-Dist: openpyxl (>=3.0.10)
Requires-Dist: pyexcel (>=0.7.0)
Requires-Dist: pymongo (>=4.3.3)
Requires-Dist: PyYAML (>=6.0)
Requires-Dist: requests (>=2.28.2)
Requires-Dist: rtoml (>=0.9.0)
Requires-Dist: spacy (>=3.5.0)
Requires-Dist: toml (>=0.10.2)
Requires-Dist: ujson (>=5.7.0)
Requires-Dist: urllib3 (>=1.26.14)
Requires-Dist: xlrd2 (>=1.3.4)
Requires-Dist: xmltodict (>=0.13.0)
